helixcli/.env
helixcli/__init__.py
helixcli/data.json
helixcli/helix.py
helixgecli-0.1.0.dist-info/licenses/LICENSE
helixgecli-0.1.0.dist-info/METADATA
helixgecli-0.1.0.dist-info/WHEEL
helixgecli-0.1.0.dist-info/entry_points.txt
helixgecli-0.1.0.dist-info/top_level.txt
helixgecli-0.1.0.dist-info/RECORD
