Metadata-Version: 2.4
Name: helixgecli
Version: 0.1.0
Summary: Helix CLI - Gene Simulation and Translation
Author: Karan
License-File: LICENSE
Requires-Dist: rich
Requires-Dist: dotenv
Requires-Dist: groq
Requires-Dist: colorama
Dynamic: license-file
